django_base_shop/__init__.py
django_base_shop/apps.py
django_base_shop/middleware.py
django_base_shop/urls.py
django_base_shop/views.py
django_base_shop/migrations/0001_initial.py
django_base_shop/migrations/0002_load_countries.py
django_base_shop/migrations/__init__.py
django_base_shop/models/__init__.py
django_base_shop/models/abstract/__init__.py
django_base_shop/models/abstract/base_cart.py
django_base_shop/models/abstract/base_cart_item.py
django_base_shop/models/abstract/base_checkout_details.py
django_base_shop/models/abstract/base_order.py
django_base_shop/models/abstract/base_order_item.py
django_base_shop/models/abstract/base_product.py
django_base_shop/models/concrete/__init__.py
django_base_shop/models/concrete/address.py
django_base_shop/models/concrete/country.py
django_base_shop/models/concrete/image.py
django_base_shop/models/concrete/shipping_option.py
django_base_shop/models/concrete/shipping_tag.py
django_base_shop-0.1.0.dist-info/LICENSE
django_base_shop-0.1.0.dist-info/METADATA
django_base_shop-0.1.0.dist-info/WHEEL
django_base_shop-0.1.0.dist-info/top_level.txt
django_base_shop-0.1.0.dist-info/RECORD
