Metadata-Version: 2.1
Name: django-base-shop
Version: 0.1.0
Summary: A basic, extendable data model for ecommerce shops using Django
Home-page: https://github.com/blakelockley/django-base-shop
Author: Blake Lockley
Author-email: bwlockley@gmail.com
License: UNKNOWN
Platform: UNKNOWN
Classifier: Programming Language :: Python :: 3
Classifier: License :: OSI Approved :: MIT License
Classifier: Operating System :: OS Independent
Classifier: Intended Audience :: Developers
Classifier: Topic :: Software Development :: Libraries :: Python Modules
Requires-Python: >=3.6.5
Requires-Dist: django (>=2.1)
Requires-Dist: pillow (==7.0.0)
